raindropmd/__init__.py
raindropmd/cli.py
raindropmd/main.py
raindropmd/templates/bookmark_template.md.j2
raindropmd/templates/custom_sections_template.md.j2
raindropmd/templates/custom_template.md.j2
raindropmd-0.1.1.dist-info/METADATA
raindropmd-0.1.1.dist-info/WHEEL
raindropmd-0.1.1.dist-info/entry_points.txt
raindropmd-0.1.1.dist-info/top_level.txt
raindropmd-0.1.1.dist-info/RECORD
