Metadata-Version: 2.4
Name: raindropmd
Version: 0.1.1
Summary: Raindrop.io CSV to Zettelkasten Markdown CLI
Author: Your Name
Requires-Python: >=3.8
Requires-Dist: click
Requires-Dist: rich
Requires-Dist: jinja2
Dynamic: author
